setup.py
mail_monitor/__init__.py
mail_monitor.egg-info/PKG-INFO
mail_monitor.egg-info/SOURCES.txt
mail_monitor.egg-info/dependency_links.txt
mail_monitor.egg-info/requires.txt
mail_monitor.egg-info/top_level.txt