Metadata-Version: 1.0
Name: mail-monitor
Version: 0.5
Summary: simple util to monitor new emails
Home-page: https://github.com/OpenJarbas/mail_monitor
Author: jarbasAI
Author-email: jarbasai@mailfence.com
License: Apache
Platform: UNKNOWN
